apeer_ometiff_library/__init__.py
apeer_ometiff_library/io.py
apeer_ometiff_library/omexmlClass.py
apeer_ometiff_library/processing.py
bue/__init__.py
bue/imagine.py
mplex_image/__init__.py
mplex_image/_version.py
mplex_image/analyze.py
mplex_image/cmif.py
mplex_image/codex.py
mplex_image/features.py
mplex_image/gating.py
mplex_image/getdata.py
mplex_image/imagine.py
mplex_image/metadata.py
mplex_image/mics.py
mplex_image/mpimage.py
mplex_image/normalize.py
mplex_image/ometiff.py
mplex_image/preprocess.py
mplex_image/process.py
mplex_image/register.py
mplex_image/segment.py
mplex_image/visualize.py
mplex_image-0.0.7.dist-info/LICENSE
mplex_image-0.0.7.dist-info/METADATA
mplex_image-0.0.7.dist-info/WHEEL
mplex_image-0.0.7.dist-info/top_level.txt
mplex_image-0.0.7.dist-info/RECORD
