Metadata-Version: 2.1
Name: mplex-image
Version: 0.0.7
Summary: A python3-based image analysis package to achieve fully-documented and reproducible visualization and analysis of bio-medical microscopy images.
Home-page: https://gitlab.com/engje/cmif
Author: Jennifer Eng
Author-email: engje@ohsu.edu
License: GPL>=3
Project-URL: Bug Reports, https://gitlab.com/engje/cmif/-/issues
Project-URL: Source, https://gitlab.com/engje/cmif
Keywords: multiplex imaging,cyclic immunofluorescence,image analysis,image processing
Platform: UNKNOWN
Classifier: Development Status :: 5 - Production/Stable
Classifier: Intended Audience :: Developers
Classifier: Intended Audience :: Science/Research
Classifier: Topic :: Scientific/Engineering :: Bio-Informatics
Classifier: Topic :: Scientific/Engineering :: Visualization
Classifier: License :: OSI Approved :: GNU General Public License v3 or later (GPLv3+)
Classifier: Programming Language :: Python :: 3.6
Requires-Python: >=3.6
Requires-Dist: biotransistor (==0.0.3)
Requires-Dist: jupyterlab
Requires-Dist: leidenalg
Requires-Dist: matplotlib
Requires-Dist: numpy
Requires-Dist: numba
Requires-Dist: napari
Requires-Dist: opencv-python
Requires-Dist: pandas
Requires-Dist: pillow
Requires-Dist: python-bioformats (==1.5.2)
Requires-Dist: python-javabridge
Requires-Dist: python-igraph
Requires-Dist: scanpy
Requires-Dist: scipy
Requires-Dist: seaborn
Requires-Dist: statsmodels
Requires-Dist: scikit-image
Requires-Dist: scikit-learn
